odoo/addons/picking_report_show_chained/README.rst
odoo/addons/picking_report_show_chained/__init__.py
odoo/addons/picking_report_show_chained/__manifest__.py
odoo/addons/picking_report_show_chained/i18n/es.po
odoo/addons/picking_report_show_chained/models/__init__.py
odoo/addons/picking_report_show_chained/models/stock_picking.py
odoo/addons/picking_report_show_chained/static/description/icon.png
odoo/addons/picking_report_show_chained/tests/__init__.py
odoo/addons/picking_report_show_chained/tests/test_picking_report_show_chained.py
odoo/addons/picking_report_show_chained/views/stock_picking_views.xml
odoo_addon_picking_report_show_chained-17.0.1.0.0.1.dist-info/METADATA
odoo_addon_picking_report_show_chained-17.0.1.0.0.1.dist-info/WHEEL
odoo_addon_picking_report_show_chained-17.0.1.0.0.1.dist-info/top_level.txt
odoo_addon_picking_report_show_chained-17.0.1.0.0.1.dist-info/RECORD
