Metadata-Version: 2.1
Name: odoo-addon-picking_report_show_chained
Version: 17.0.1.0.0.1
Requires-Python: >=3.10
Requires-Dist: odoo>=17.0a,<17.1dev
Summary: Display previous and subsequent pickings in pickings PDFs
Home-page: https://github.com/sygel-technology/sy-stock-logistics-reporting
License: AGPL-3
Author: Sygel, Odoo Community Association (OCA)
Author-email: support@odoo-community.org
Classifier: Programming Language :: Python
Classifier: Framework :: Odoo
Classifier: Framework :: Odoo :: 17.0
Classifier: License :: OSI Approved :: GNU Affero General Public License v3
